setup.py
iridium/__init__.py
iridium/actions.py
iridium/browser.py
iridium.egg-info/PKG-INFO
iridium.egg-info/SOURCES.txt
iridium.egg-info/dependency_links.txt
iridium.egg-info/requires.txt
iridium.egg-info/top_level.txt
iridium/_webdriwers/linux64_chromedriver
iridium/_webdriwers/mac64_chromedriver
iridium/_webdriwers/win32_chromedriver.exe