Metadata-Version: 1.2
Name: iridium
Version: 0.1.61
Summary: Selenium wrapper
Home-page: https://github.com/RusJr/iridium
Author: Rus Jr
Author-email: binderrrr@gmail.com
License: MIT
Keywords: selenium chrome browser
Platform: UNKNOWN
Requires-Python: >=3.5
